<?xml version="1.0" encoding="utf-8"?>
<command id="4102854">
 <sentence>
  4- The Kiosk should be equipped with wireless communication equipment , and a mechanist to open and close the gate automatically .
 </sentence>
 <tokens>
  <token id="1" lemma="4-" pos="LS" surface="4-"/>
  <token id="2" lemma="the" pos="DT" surface="The"/>
  <token id="3" lemma="kiosk" pos="NNP" surface="Kiosk"/>
  <token id="4" lemma="should" pos="MD" surface="should"/>
  <token id="5" lemma="be" pos="VB" surface="be"/>
  <token id="6" lemma="equip" pos="VBN" surface="equipped"/>
  <token id="7" lemma="with" pos="IN" surface="with"/>
  <token id="8" lemma="wireless" pos="JJ" surface="wireless"/>
  <token id="9" lemma="communication" pos="NN" surface="communication"/>
  <token id="10" lemma="equipment" pos="NN" surface="equipment"/>
  <token id="11" lemma="," pos="," surface=","/>
  <token id="12" lemma="and" pos="CC" surface="and"/>
  <token id="13" lemma="a" pos="DT" surface="a"/>
  <token id="14" lemma="mechanist" pos="NN" surface="mechanist"/>
  <token id="15" lemma="to" pos="TO" surface="to"/>
  <token id="16" lemma="open" pos="VB" surface="open"/>
  <token id="17" lemma="and" pos="CC" surface="and"/>
  <token id="18" lemma="close" pos="VB" surface="close"/>
  <token id="19" lemma="the" pos="DT" surface="the"/>
  <token id="20" lemma="gate" pos="NN" surface="gate"/>
  <token id="21" lemma="automatically" pos="RB" surface="automatically"/>
  <token id="22" lemma="." pos="." surface="."/>
 </tokens>
 <dependencies>
  <dep from="6" to="1" type="meta"/>
  <dep from="3" to="2" type="det"/>
  <dep from="6" to="3" type="nsubjpass"/>
  <dep from="6" to="4" type="aux"/>
  <dep from="6" to="5" type="auxpass"/>
  <dep from="0" to="6" type="root"/>
  <dep from="6" to="7" type="prep"/>
  <dep from="10" to="8" type="amod"/>
  <dep from="10" to="9" type="compound"/>
  <dep from="7" to="10" type="pobj"/>
  <dep from="6" to="11" type="punct"/>
  <dep from="6" to="12" type="cc"/>
  <dep from="14" to="13" type="det"/>
  <dep from="6" to="14" type="conj"/>
  <dep from="16" to="15" type="aux"/>
  <dep from="14" to="16" type="acl"/>
  <dep from="16" to="17" type="cc"/>
  <dep from="16" to="18" type="conj"/>
  <dep from="20" to="19" type="det"/>
  <dep from="18" to="20" type="dobj"/>
  <dep from="18" to="21" type="advmod"/>
  <dep from="6" to="22" type="punct"/>
 </dependencies>
 <semantics>
  <frameSemantics>
   <frame name="Buildings">
    <lexicalUnit>
     <token id="3"/>
    </lexicalUnit>
    <frameElement type="Building">
     <token id="3"/>
    </frameElement>
   </frame>
   <frame name="Desirable_event">
    <lexicalUnit>
     <token id="4"/>
    </lexicalUnit>
    <frameElement type="State_of_affairs">
     <token id="2"/>
     <token id="3"/>
    </frameElement>
    <frameElement type="State_of_affairs">
     <token id="5"/>
     <token id="6"/>
     <token id="7"/>
     <token id="8"/>
     <token id="9"/>
     <token id="10"/>
     <token id="11"/>
     <token id="12"/>
     <token id="13"/>
     <token id="14"/>
     <token id="15"/>
     <token id="16"/>
     <token id="17"/>
     <token id="18"/>
     <token id="19"/>
     <token id="20"/>
     <token id="21"/>
    </frameElement>
   </frame>
   <frame name="Supply">
    <lexicalUnit>
     <token id="6"/>
    </lexicalUnit>
    <frameElement type="Recipient">
     <token id="2"/>
     <token id="3"/>
    </frameElement>
    <frameElement type="Theme">
     <token id="7"/>
     <token id="8"/>
     <token id="9"/>
     <token id="10"/>
     <token id="11"/>
     <token id="12"/>
     <token id="13"/>
     <token id="14"/>
    </frameElement>
    <frameElement type="Imposed_purpose">
     <token id="15"/>
     <token id="16"/>
     <token id="17"/>
     <token id="18"/>
     <token id="19"/>
     <token id="20"/>
     <token id="21"/>
    </frameElement>
   </frame>
   <frame name="Communication">
    <lexicalUnit>
     <token id="9"/>
    </lexicalUnit>
    <frameElement type="Message">
     <token id="9"/>
    </frameElement>
    <frameElement type="Medium">
     <token id="8"/>
    </frameElement>
    <frameElement type="Medium">
     <token id="10"/>
    </frameElement>
   </frame>
   <frame name="Gizmo">
    <lexicalUnit>
     <token id="10"/>
    </lexicalUnit>
    <frameElement type="Gizmo">
     <token id="10"/>
    </frameElement>
    <frameElement type="Use">
     <token id="9"/>
    </frameElement>
    <frameElement type="Descriptor">
     <token id="8"/>
    </frameElement>
   </frame>
  </frameSemantics>
 </semantics>
</command>