<?xml version="1.0" encoding="utf-8"?>
<command id="2824222">
 <sentence>
  Ten shirt-sleeved ringers stand in a circle , one foot ahead of the other in a prize-fighter 's stance , each pulling a rope that disappears through a small hole in the high ceiling of the ringing chamber .
 </sentence>
 <tokens>
  <token id="1" lemma="ten" pos="CD" surface="Ten"/>
  <token id="2" lemma="shirt-sleeved" pos="JJ" surface="shirt-sleeved"/>
  <token id="3" lemma="ringer" pos="NNS" surface="ringers"/>
  <token id="4" lemma="stand" pos="VBP" surface="stand"/>
  <token id="5" lemma="in" pos="IN" surface="in"/>
  <token id="6" lemma="a" pos="DT" surface="a"/>
  <token id="7" lemma="circle" pos="NN" surface="circle"/>
  <token id="8" lemma="," pos="," surface=","/>
  <token id="9" lemma="one" pos="CD" surface="one"/>
  <token id="10" lemma="foot" pos="NN" surface="foot"/>
  <token id="11" lemma="ahead" pos="RB" surface="ahead"/>
  <token id="12" lemma="of" pos="IN" surface="of"/>
  <token id="13" lemma="the" pos="DT" surface="the"/>
  <token id="14" lemma="other" pos="JJ" surface="other"/>
  <token id="15" lemma="in" pos="IN" surface="in"/>
  <token id="16" lemma="a" pos="DT" surface="a"/>
  <token id="17" lemma="prize-fighter" pos="NN" surface="prize-fighter"/>
  <token id="18" lemma="'s" pos="POS" surface="'s"/>
  <token id="19" lemma="stance" pos="NN" surface="stance"/>
  <token id="20" lemma="," pos="," surface=","/>
  <token id="21" lemma="each" pos="DT" surface="each"/>
  <token id="22" lemma="pull" pos="VBG" surface="pulling"/>
  <token id="23" lemma="a" pos="DT" surface="a"/>
  <token id="24" lemma="rope" pos="NN" surface="rope"/>
  <token id="25" lemma="that" pos="WDT" surface="that"/>
  <token id="26" lemma="disappear" pos="VBZ" surface="disappears"/>
  <token id="27" lemma="through" pos="IN" surface="through"/>
  <token id="28" lemma="a" pos="DT" surface="a"/>
  <token id="29" lemma="small" pos="JJ" surface="small"/>
  <token id="30" lemma="hole" pos="NN" surface="hole"/>
  <token id="31" lemma="in" pos="IN" surface="in"/>
  <token id="32" lemma="the" pos="DT" surface="the"/>
  <token id="33" lemma="high" pos="JJ" surface="high"/>
  <token id="34" lemma="ceiling" pos="NN" surface="ceiling"/>
  <token id="35" lemma="of" pos="IN" surface="of"/>
  <token id="36" lemma="the" pos="DT" surface="the"/>
  <token id="37" lemma="ring" pos="VBG" surface="ringing"/>
  <token id="38" lemma="chamber" pos="NN" surface="chamber"/>
  <token id="39" lemma="." pos="." surface="."/>
 </tokens>
 <dependencies>
  <dep from="3" to="1" type="nummod"/>
  <dep from="3" to="2" type="amod"/>
  <dep from="4" to="3" type="nsubj"/>
  <dep from="0" to="4" type="root"/>
  <dep from="4" to="5" type="prep"/>
  <dep from="7" to="6" type="det"/>
  <dep from="5" to="7" type="pobj"/>
  <dep from="4" to="8" type="punct"/>
  <dep from="10" to="9" type="nummod"/>
  <dep from="11" to="10" type="npadvmod"/>
  <dep from="4" to="11" type="advmod"/>
  <dep from="11" to="12" type="prep"/>
  <dep from="14" to="13" type="det"/>
  <dep from="12" to="14" type="pobj"/>
  <dep from="11" to="15" type="prep"/>
  <dep from="17" to="16" type="det"/>
  <dep from="19" to="17" type="poss"/>
  <dep from="17" to="18" type="case"/>
  <dep from="15" to="19" type="pobj"/>
  <dep from="4" to="20" type="punct"/>
  <dep from="22" to="21" type="nsubj"/>
  <dep from="4" to="22" type="advcl"/>
  <dep from="24" to="23" type="det"/>
  <dep from="22" to="24" type="dobj"/>
  <dep from="26" to="25" type="nsubj"/>
  <dep from="24" to="26" type="relcl"/>
  <dep from="26" to="27" type="prep"/>
  <dep from="30" to="28" type="det"/>
  <dep from="30" to="29" type="amod"/>
  <dep from="27" to="30" type="pobj"/>
  <dep from="30" to="31" type="prep"/>
  <dep from="34" to="32" type="det"/>
  <dep from="34" to="33" type="amod"/>
  <dep from="31" to="34" type="pobj"/>
  <dep from="34" to="35" type="prep"/>
  <dep from="38" to="36" type="det"/>
  <dep from="38" to="37" type="amod"/>
  <dep from="35" to="38" type="pobj"/>
  <dep from="4" to="39" type="punct"/>
 </dependencies>
 <semantics>
  <frameSemantics>
   <frame name="Posture">
    <lexicalUnit>
     <token id="4"/>
    </lexicalUnit>
    <frameElement type="Agent">
     <token id="1"/>
     <token id="2"/>
     <token id="3"/>
    </frameElement>
    <frameElement type="Depictive">
     <token id="5"/>
     <token id="6"/>
     <token id="7"/>
    </frameElement>
    <frameElement type="Depictive">
     <token id="9"/>
     <token id="10"/>
     <token id="11"/>
     <token id="12"/>
     <token id="13"/>
     <token id="14"/>
     <token id="15"/>
     <token id="16"/>
     <token id="17"/>
     <token id="18"/>
     <token id="19"/>
    </frameElement>
   </frame>
   <frame name="Cause_to_make_noise">
    <lexicalUnit>
     <token id="3"/>
    </lexicalUnit>
    <frameElement type="Agent">
     <token id="3"/>
    </frameElement>
   </frame>
   <frame name="Posture">
    <lexicalUnit>
     <token id="19"/>
    </lexicalUnit>
    <frameElement type="Agent">
     <token id="1"/>
     <token id="2"/>
     <token id="3"/>
    </frameElement>
   </frame>
   <frame name="Body_parts">
    <lexicalUnit>
     <token id="10"/>
    </lexicalUnit>
    <frameElement type="Body_part">
     <token id="10"/>
    </frameElement>
   </frame>
   <frame name="Manipulation">
    <lexicalUnit>
     <token id="22"/>
    </lexicalUnit>
    <frameElement type="Agent">
     <token id="21"/>
    </frameElement>
    <frameElement type="Entity">
     <token id="23"/>
     <token id="24"/>
     <token id="25"/>
     <token id="26"/>
     <token id="27"/>
     <token id="28"/>
     <token id="29"/>
     <token id="30"/>
     <token id="31"/>
     <token id="32"/>
     <token id="33"/>
     <token id="34"/>
     <token id="35"/>
     <token id="36"/>
     <token id="37"/>
     <token id="38"/>
    </frameElement>
   </frame>
   <frame name="Connectors">
    <lexicalUnit>
     <token id="24"/>
    </lexicalUnit>
    <frameElement type="Connector">
     <token id="24"/>
    </frameElement>
   </frame>
   <frame name="Architectural_part">
    <lexicalUnit>
     <token id="34"/>
    </lexicalUnit>
    <frameElement type="Part">
     <token id="34"/>
    </frameElement>
    <frameElement type="Whole">
     <token id="35"/>
     <token id="36"/>
     <token id="37"/>
     <token id="38"/>
    </frameElement>
   </frame>
   <frame name="Building_subparts">
    <lexicalUnit>
     <token id="38"/>
    </lexicalUnit>
    <frameElement type="Building_part">
     <token id="38"/>
    </frameElement>
    <frameElement type="Use">
     <token id="37"/>
    </frameElement>
   </frame>
   <frame name="Cause_to_make_noise">
    <lexicalUnit>
     <token id="37"/>
    </lexicalUnit>
   </frame>
   <frame name="Increment">
    <lexicalUnit>
     <token id="14"/>
    </lexicalUnit>
    <frameElement type="Added_set">
     <token id="14"/>
    </frameElement>
   </frame>
   <frame name="Cardinal_numbers">
    <lexicalUnit>
     <token id="1"/>
    </lexicalUnit>
    <frameElement type="Number">
     <token id="1"/>
    </frameElement>
    <frameElement type="Entity">
     <token id="2"/>
     <token id="3"/>
    </frameElement>
   </frame>
   <frame name="Shapes">
    <lexicalUnit>
     <token id="7"/>
    </lexicalUnit>
    <frameElement type="Shape">
     <token id="7"/>
    </frameElement>
   </frame>
   <frame name="Size">
    <lexicalUnit>
     <token id="29"/>
    </lexicalUnit>
    <frameElement type="Entity">
     <token id="30"/>
    </frameElement>
   </frame>
   <frame name="Measurable_attributes">
    <lexicalUnit>
     <token id="33"/>
    </lexicalUnit>
    <frameElement type="Entity">
     <token id="34"/>
    </frameElement>
   </frame>
  </frameSemantics>
 </semantics>
</command>