<?xml version="1.0" encoding="utf-8"?>
<command id="4148372">
 <sentence>
  It was Garcia , then , who had an enterprise , and apparently a criminal enterprise , in hand that night in the course of which he met his death .
 </sentence>
 <tokens>
  <token id="1" lemma="-PRON-" pos="PRP" surface="It"/>
  <token id="2" lemma="be" pos="VBD" surface="was"/>
  <token id="3" lemma="garcia" pos="NNP" surface="Garcia"/>
  <token id="4" lemma="," pos="," surface=","/>
  <token id="5" lemma="then" pos="RB" surface="then"/>
  <token id="6" lemma="," pos="," surface=","/>
  <token id="7" lemma="who" pos="WP" surface="who"/>
  <token id="8" lemma="have" pos="VBD" surface="had"/>
  <token id="9" lemma="an" pos="DT" surface="an"/>
  <token id="10" lemma="enterprise" pos="NN" surface="enterprise"/>
  <token id="11" lemma="," pos="," surface=","/>
  <token id="12" lemma="and" pos="CC" surface="and"/>
  <token id="13" lemma="apparently" pos="RB" surface="apparently"/>
  <token id="14" lemma="a" pos="DT" surface="a"/>
  <token id="15" lemma="criminal" pos="JJ" surface="criminal"/>
  <token id="16" lemma="enterprise" pos="NN" surface="enterprise"/>
  <token id="17" lemma="," pos="," surface=","/>
  <token id="18" lemma="in" pos="IN" surface="in"/>
  <token id="19" lemma="hand" pos="NN" surface="hand"/>
  <token id="20" lemma="that" pos="DT" surface="that"/>
  <token id="21" lemma="night" pos="NN" surface="night"/>
  <token id="22" lemma="in" pos="IN" surface="in"/>
  <token id="23" lemma="the" pos="DT" surface="the"/>
  <token id="24" lemma="course" pos="NN" surface="course"/>
  <token id="25" lemma="of" pos="IN" surface="of"/>
  <token id="26" lemma="which" pos="WDT" surface="which"/>
  <token id="27" lemma="-PRON-" pos="PRP" surface="he"/>
  <token id="28" lemma="meet" pos="VBD" surface="met"/>
  <token id="29" lemma="-PRON-" pos="PRP$" surface="his"/>
  <token id="30" lemma="death" pos="NN" surface="death"/>
  <token id="31" lemma="." pos="." surface="."/>
 </tokens>
 <dependencies>
  <dep from="2" to="1" type="nsubj"/>
  <dep from="0" to="2" type="root"/>
  <dep from="2" to="3" type="attr"/>
  <dep from="3" to="4" type="punct"/>
  <dep from="2" to="5" type="advmod"/>
  <dep from="2" to="6" type="punct"/>
  <dep from="8" to="7" type="nsubj"/>
  <dep from="2" to="8" type="ccomp"/>
  <dep from="10" to="9" type="det"/>
  <dep from="8" to="10" type="dobj"/>
  <dep from="8" to="11" type="punct"/>
  <dep from="8" to="12" type="cc"/>
  <dep from="16" to="13" type="advmod"/>
  <dep from="16" to="14" type="det"/>
  <dep from="16" to="15" type="amod"/>
  <dep from="8" to="16" type="conj"/>
  <dep from="16" to="17" type="punct"/>
  <dep from="16" to="18" type="prep"/>
  <dep from="18" to="19" type="pobj"/>
  <dep from="21" to="20" type="det"/>
  <dep from="16" to="21" type="npadvmod"/>
  <dep from="16" to="22" type="prep"/>
  <dep from="24" to="23" type="det"/>
  <dep from="22" to="24" type="pobj"/>
  <dep from="28" to="25" type="prep"/>
  <dep from="25" to="26" type="pobj"/>
  <dep from="28" to="27" type="nsubj"/>
  <dep from="24" to="28" type="relcl"/>
  <dep from="30" to="29" type="poss"/>
  <dep from="28" to="30" type="dobj"/>
  <dep from="2" to="31" type="punct"/>
 </dependencies>
 <semantics>
  <frameSemantics>
   <frame name="Death">
    <lexicalUnit>
     <token id="30"/>
    </lexicalUnit>
    <frameElement type="Protagonist">
     <token id="29"/>
    </frameElement>
   </frame>
   <frame name="Calendric_unit">
    <lexicalUnit>
     <token id="21"/>
    </lexicalUnit>
    <frameElement type="Unit">
     <token id="21"/>
    </frameElement>
    <frameElement type="Salient_event">
     <token id="22"/>
     <token id="23"/>
     <token id="24"/>
     <token id="25"/>
     <token id="26"/>
     <token id="27"/>
     <token id="28"/>
     <token id="29"/>
     <token id="30"/>
    </frameElement>
   </frame>
  </frameSemantics>
 </semantics>
</command>