<?xml version="1.0" encoding="utf-8"?>
<command id="149_t_0">
 <sentence>
  Stocks rallied for a second session Thursday , boosted by falling oil prices and ongoing relief that the presidential election has passed without incident .
 </sentence>
 <tokens>
  <token id="1" lemma="Stock" pos="NNS" surface="Stocks"/>
  <token id="2" lemma="rally" pos="VBD" surface="rallied"/>
  <token id="3" lemma="for" pos="IN" surface="for"/>
  <token id="4" lemma="a" pos="DT" surface="a"/>
  <token id="5" lemma="second" pos="JJ" surface="second"/>
  <token id="6" lemma="session" pos="NN" surface="session"/>
  <token id="7" lemma="Thursday" pos="NNP" surface="Thursday"/>
  <token id="8" lemma="," pos="PUNC," surface=","/>
  <token id="9" lemma="boost" pos="VBN" surface="boosted"/>
  <token id="10" lemma="by" pos="IN" surface="by"/>
  <token id="11" lemma="fall" pos="VBG" surface="falling"/>
  <token id="12" lemma="oil" pos="NN" surface="oil"/>
  <token id="13" lemma="price" pos="NNS" surface="prices"/>
  <token id="14" lemma="and" pos="CC" surface="and"/>
  <token id="15" lemma="ongoing" pos="JJ" surface="ongoing"/>
  <token id="16" lemma="relief" pos="NN" surface="relief"/>
  <token id="17" lemma="that" pos="IN" surface="that"/>
  <token id="18" lemma="the" pos="DT" surface="the"/>
  <token id="19" lemma="presidential" pos="JJ" surface="presidential"/>
  <token id="20" lemma="election" pos="NN" surface="election"/>
  <token id="21" lemma="have" pos="VBZ" surface="has"/>
  <token id="22" lemma="pass" pos="VBN" surface="passed"/>
  <token id="23" lemma="without" pos="IN" surface="without"/>
  <token id="24" lemma="incident" pos="NN" surface="incident"/>
  <token id="25" lemma="." pos="PUNC." surface="."/>
 </tokens>
 <dependencies>
  <dep from="2" to="1" type="unknown"/>
  <dep from="0" to="2" type="root"/>
  <dep from="2" to="3" type="unknown"/>
  <dep from="6" to="4" type="unknown"/>
  <dep from="6" to="5" type="unknown"/>
  <dep from="3" to="6" type="unknown"/>
  <dep from="2" to="7" type="unknown"/>
  <dep from="7" to="8" type="unknown"/>
  <dep from="2" to="9" type="unknown"/>
  <dep from="9" to="10" type="unknown"/>
  <dep from="13" to="11" type="unknown"/>
  <dep from="13" to="12" type="unknown"/>
  <dep from="10" to="13" type="unknown"/>
  <dep from="13" to="14" type="unknown"/>
  <dep from="16" to="15" type="unknown"/>
  <dep from="13" to="16" type="unknown"/>
  <dep from="16" to="17" type="unknown"/>
  <dep from="20" to="18" type="unknown"/>
  <dep from="20" to="19" type="unknown"/>
  <dep from="21" to="20" type="unknown"/>
  <dep from="17" to="21" type="unknown"/>
  <dep from="21" to="22" type="unknown"/>
  <dep from="22" to="23" type="unknown"/>
  <dep from="23" to="24" type="unknown"/>
  <dep from="24" to="25" type="unknown"/>
 </dependencies>
 <semantics>
  <frameSemantics>
   <frame name="Unknown">
    <lexicalUnit>
     <token id="2"/>
    </lexicalUnit>
    <frameElement type="Fe1">
     <token id="1"/>
    </frameElement>
    <frameElement type="Fe2">
     <token id="3"/>
     <token id="4"/>
     <token id="5"/>
     <token id="6"/>
    </frameElement>
    <frameElement type="Fe3">
     <token id="7"/>
     <token id="8"/>
    </frameElement>
   </frame>
   <frame name="Assistance">
    <lexicalUnit>
     <token id="9"/>
    </lexicalUnit>
    <frameElement type="Benefitted_party">
     <token id="1"/>
    </frameElement>
    <frameElement type="Helper">
     <token id="10"/>
     <token id="11"/>
     <token id="12"/>
     <token id="13"/>
     <token id="14"/>
     <token id="15"/>
     <token id="16"/>
     <token id="17"/>
     <token id="18"/>
     <token id="19"/>
     <token id="20"/>
     <token id="21"/>
     <token id="22"/>
     <token id="23"/>
     <token id="24"/>
     <token id="25"/>
    </frameElement>
   </frame>
   <frame name="Change_position_on_a_scale">
    <lexicalUnit>
     <token id="11"/>
    </lexicalUnit>
    <frameElement type="Attribute">
     <token id="13"/>
    </frameElement>
    <frameElement type="Item">
     <token id="12"/>
    </frameElement>
   </frame>
  </frameSemantics>
 </semantics>
</command>