<?xml version="1.0" encoding="utf-8"?>
<command id="759_t_0">
 <sentence>
  Concerned about the impact of federal regulations on the prices of food and commodities that the federal government purchases , you requested that we provide details about federal agencies ' purchases of food and/or agricultural commodities from fiscal year 1997 through fiscal year 1999 .
 </sentence>
 <tokens>
  <token id="1" lemma="concern" pos="VBN" surface="Concerned"/>
  <token id="2" lemma="about" pos="IN" surface="about"/>
  <token id="3" lemma="the" pos="DT" surface="the"/>
  <token id="4" lemma="impact" pos="NN" surface="impact"/>
  <token id="5" lemma="of" pos="IN" surface="of"/>
  <token id="6" lemma="federal" pos="JJ" surface="federal"/>
  <token id="7" lemma="regulation" pos="NNS" surface="regulations"/>
  <token id="8" lemma="on" pos="IN" surface="on"/>
  <token id="9" lemma="the" pos="DT" surface="the"/>
  <token id="10" lemma="price" pos="NNS" surface="prices"/>
  <token id="11" lemma="of" pos="IN" surface="of"/>
  <token id="12" lemma="food" pos="NN" surface="food"/>
  <token id="13" lemma="and" pos="CC" surface="and"/>
  <token id="14" lemma="commodity" pos="NNS" surface="commodities"/>
  <token id="15" lemma="that" pos="WDT" surface="that"/>
  <token id="16" lemma="the" pos="DT" surface="the"/>
  <token id="17" lemma="federal" pos="JJ" surface="federal"/>
  <token id="18" lemma="government" pos="NN" surface="government"/>
  <token id="19" lemma="purchase" pos="VBZ" surface="purchases"/>
  <token id="20" lemma="," pos="PUNC," surface=","/>
  <token id="21" lemma="you" pos="PRP" surface="you"/>
  <token id="22" lemma="request" pos="VBD" surface="requested"/>
  <token id="23" lemma="that" pos="IN" surface="that"/>
  <token id="24" lemma="we" pos="PRP" surface="we"/>
  <token id="25" lemma="provide" pos="VB" surface="provide"/>
  <token id="26" lemma="detail" pos="NNS" surface="details"/>
  <token id="27" lemma="about" pos="IN" surface="about"/>
  <token id="28" lemma="federal" pos="JJ" surface="federal"/>
  <token id="29" lemma="agency" pos="NNS" surface="agencies"/>
  <token id="30" lemma="&amp;#39;" pos="POS" surface="'"/>
  <token id="31" lemma="purchase" pos="NNS" surface="purchases"/>
  <token id="32" lemma="of" pos="IN" surface="of"/>
  <token id="33" lemma="food" pos="NN" surface="food"/>
  <token id="34" lemma="&amp;#60;unknown&amp;#62;" pos="CC" surface="and/or"/>
  <token id="35" lemma="agricultural" pos="JJ" surface="agricultural"/>
  <token id="36" lemma="commodity" pos="NNS" surface="commodities"/>
  <token id="37" lemma="from" pos="IN" surface="from"/>
  <token id="38" lemma="fiscal" pos="JJ" surface="fiscal"/>
  <token id="39" lemma="year" pos="NN" surface="year"/>
  <token id="40" lemma="@card@" pos="CD" surface="1997"/>
  <token id="41" lemma="through" pos="IN" surface="through"/>
  <token id="42" lemma="fiscal" pos="JJ" surface="fiscal"/>
  <token id="43" lemma="year" pos="NN" surface="year"/>
  <token id="44" lemma="@card@" pos="CD" surface="1999"/>
  <token id="45" lemma="." pos="PUNC." surface="."/>
 </tokens>
 <dependencies>
  <dep from="22" to="1" type="unknown"/>
  <dep from="1" to="2" type="unknown"/>
  <dep from="4" to="3" type="unknown"/>
  <dep from="2" to="4" type="unknown"/>
  <dep from="4" to="5" type="unknown"/>
  <dep from="7" to="6" type="unknown"/>
  <dep from="5" to="7" type="unknown"/>
  <dep from="4" to="8" type="unknown"/>
  <dep from="10" to="9" type="unknown"/>
  <dep from="8" to="10" type="unknown"/>
  <dep from="10" to="11" type="unknown"/>
  <dep from="14" to="12" type="unknown"/>
  <dep from="14" to="13" type="unknown"/>
  <dep from="11" to="14" type="unknown"/>
  <dep from="14" to="15" type="unknown"/>
  <dep from="18" to="16" type="unknown"/>
  <dep from="18" to="17" type="unknown"/>
  <dep from="19" to="18" type="unknown"/>
  <dep from="15" to="19" type="unknown"/>
  <dep from="19" to="20" type="unknown"/>
  <dep from="22" to="21" type="unknown"/>
  <dep from="0" to="22" type="root"/>
  <dep from="22" to="23" type="unknown"/>
  <dep from="25" to="24" type="unknown"/>
  <dep from="23" to="25" type="unknown"/>
  <dep from="25" to="26" type="unknown"/>
  <dep from="26" to="27" type="unknown"/>
  <dep from="30" to="28" type="unknown"/>
  <dep from="30" to="29" type="unknown"/>
  <dep from="31" to="30" type="unknown"/>
  <dep from="27" to="31" type="unknown"/>
  <dep from="31" to="32" type="unknown"/>
  <dep from="32" to="33" type="unknown"/>
  <dep from="33" to="34" type="unknown"/>
  <dep from="36" to="35" type="unknown"/>
  <dep from="33" to="36" type="unknown"/>
  <dep from="31" to="37" type="unknown"/>
  <dep from="39" to="38" type="unknown"/>
  <dep from="37" to="39" type="unknown"/>
  <dep from="39" to="40" type="unknown"/>
  <dep from="25" to="41" type="unknown"/>
  <dep from="43" to="42" type="unknown"/>
  <dep from="41" to="43" type="unknown"/>
  <dep from="43" to="44" type="unknown"/>
  <dep from="43" to="45" type="unknown"/>
 </dependencies>
 <semantics>
  <frameSemantics>
   <frame name="Commerce_buy">
    <lexicalUnit>
     <token id="19"/>
    </lexicalUnit>
    <frameElement type="Goods">
     <token id="15"/>
    </frameElement>
   </frame>
   <frame name="Leadership">
    <lexicalUnit>
     <token id="18"/>
    </lexicalUnit>
    <frameElement type="Jurisdiction">
     <token id="17"/>
    </frameElement>
   </frame>
   <frame name="Anaphora">
    <lexicalUnit>
     <token id="15"/>
    </lexicalUnit>
    <frameElement type="Antecedent">
     <token id="12"/>
     <token id="13"/>
     <token id="14"/>
    </frameElement>
   </frame>
  </frameSemantics>
 </semantics>
</command>