<?xml version="1.0" encoding="utf-8"?>
<command id="1282501">
 <sentence>
  Japan was one of Laos 's most substantial aid donors , assistance having totalled 1,800 million yen in 1988 ( compared with 1,000 million yen in 1983 ) .
 </sentence>
 <tokens>
  <token id="1" lemma="japan" pos="NNP" surface="Japan"/>
  <token id="2" lemma="be" pos="VBD" surface="was"/>
  <token id="3" lemma="one" pos="CD" surface="one"/>
  <token id="4" lemma="of" pos="IN" surface="of"/>
  <token id="5" lemma="laos" pos="NNP" surface="Laos"/>
  <token id="6" lemma="'s" pos="POS" surface="'s"/>
  <token id="7" lemma="most" pos="RBS" surface="most"/>
  <token id="8" lemma="substantial" pos="JJ" surface="substantial"/>
  <token id="9" lemma="aid" pos="NN" surface="aid"/>
  <token id="10" lemma="donor" pos="NNS" surface="donors"/>
  <token id="11" lemma="," pos="," surface=","/>
  <token id="12" lemma="assistance" pos="NN" surface="assistance"/>
  <token id="13" lemma="have" pos="VBG" surface="having"/>
  <token id="14" lemma="total" pos="VBN" surface="totalled"/>
  <token id="15" lemma="1,800" pos="CD" surface="1,800"/>
  <token id="16" lemma="million" pos="CD" surface="million"/>
  <token id="17" lemma="yen" pos="NN" surface="yen"/>
  <token id="18" lemma="in" pos="IN" surface="in"/>
  <token id="19" lemma="1988" pos="CD" surface="1988"/>
  <token id="20" lemma="(" pos="-LRB-" surface="("/>
  <token id="21" lemma="compare" pos="VBN" surface="compared"/>
  <token id="22" lemma="with" pos="IN" surface="with"/>
  <token id="23" lemma="1,000" pos="CD" surface="1,000"/>
  <token id="24" lemma="million" pos="CD" surface="million"/>
  <token id="25" lemma="yen" pos="NN" surface="yen"/>
  <token id="26" lemma="in" pos="IN" surface="in"/>
  <token id="27" lemma="1983" pos="CD" surface="1983"/>
  <token id="28" lemma=")" pos="-RRB-" surface=")"/>
  <token id="29" lemma="." pos="." surface="."/>
 </tokens>
 <dependencies>
  <dep from="2" to="1" type="nsubj"/>
  <dep from="0" to="2" type="root"/>
  <dep from="2" to="3" type="attr"/>
  <dep from="3" to="4" type="prep"/>
  <dep from="10" to="5" type="poss"/>
  <dep from="5" to="6" type="case"/>
  <dep from="8" to="7" type="advmod"/>
  <dep from="10" to="8" type="amod"/>
  <dep from="10" to="9" type="compound"/>
  <dep from="4" to="10" type="pobj"/>
  <dep from="3" to="11" type="punct"/>
  <dep from="14" to="12" type="nsubj"/>
  <dep from="14" to="13" type="aux"/>
  <dep from="2" to="14" type="conj"/>
  <dep from="16" to="15" type="compound"/>
  <dep from="17" to="16" type="nummod"/>
  <dep from="14" to="17" type="dobj"/>
  <dep from="14" to="18" type="prep"/>
  <dep from="18" to="19" type="pobj"/>
  <dep from="2" to="20" type="punct"/>
  <dep from="2" to="21" type="prep"/>
  <dep from="21" to="22" type="prep"/>
  <dep from="24" to="23" type="compound"/>
  <dep from="25" to="24" type="nummod"/>
  <dep from="22" to="25" type="pobj"/>
  <dep from="25" to="26" type="prep"/>
  <dep from="26" to="27" type="pobj"/>
  <dep from="2" to="28" type="punct"/>
  <dep from="2" to="29" type="punct"/>
 </dependencies>
 <semantics>
  <frameSemantics>
   <frame name="Giving">
    <lexicalUnit>
     <token id="10"/>
    </lexicalUnit>
    <frameElement type="Theme">
     <token id="9"/>
    </frameElement>
    <frameElement type="Donor">
     <token id="1"/>
    </frameElement>
    <frameElement type="Recipient">
     <token id="5"/>
     <token id="6"/>
    </frameElement>
    <frameElement type="Manner">
     <token id="7"/>
     <token id="8"/>
    </frameElement>
   </frame>
  </frameSemantics>
 </semantics>
</command>