<?xml version="1.0" encoding="utf-8"?>
<command id="398840">
 <sentence>
  Then she disappeared , until Jane opened the airing cupboard and met the unblinking gaze of Fluff and Titch side by side on the blankets .
 </sentence>
 <tokens>
  <token id="1" lemma="then" pos="RB" surface="Then"/>
  <token id="2" lemma="-PRON-" pos="PRP" surface="she"/>
  <token id="3" lemma="disappear" pos="VBD" surface="disappeared"/>
  <token id="4" lemma="," pos="," surface=","/>
  <token id="5" lemma="until" pos="IN" surface="until"/>
  <token id="6" lemma="jane" pos="NNP" surface="Jane"/>
  <token id="7" lemma="open" pos="VBD" surface="opened"/>
  <token id="8" lemma="the" pos="DT" surface="the"/>
  <token id="9" lemma="airing" pos="NN" surface="airing"/>
  <token id="10" lemma="cupboard" pos="NN" surface="cupboard"/>
  <token id="11" lemma="and" pos="CC" surface="and"/>
  <token id="12" lemma="meet" pos="VBD" surface="met"/>
  <token id="13" lemma="the" pos="DT" surface="the"/>
  <token id="14" lemma="unblinking" pos="JJ" surface="unblinking"/>
  <token id="15" lemma="gaze" pos="NN" surface="gaze"/>
  <token id="16" lemma="of" pos="IN" surface="of"/>
  <token id="17" lemma="fluff" pos="NNP" surface="Fluff"/>
  <token id="18" lemma="and" pos="CC" surface="and"/>
  <token id="19" lemma="titch" pos="NNP" surface="Titch"/>
  <token id="20" lemma="side" pos="NN" surface="side"/>
  <token id="21" lemma="by" pos="IN" surface="by"/>
  <token id="22" lemma="side" pos="NN" surface="side"/>
  <token id="23" lemma="on" pos="IN" surface="on"/>
  <token id="24" lemma="the" pos="DT" surface="the"/>
  <token id="25" lemma="blanket" pos="NNS" surface="blankets"/>
  <token id="26" lemma="." pos="." surface="."/>
 </tokens>
 <dependencies>
  <dep from="3" to="1" type="advmod"/>
  <dep from="3" to="2" type="nsubj"/>
  <dep from="0" to="3" type="root"/>
  <dep from="3" to="4" type="punct"/>
  <dep from="7" to="5" type="mark"/>
  <dep from="7" to="6" type="nsubj"/>
  <dep from="3" to="7" type="advcl"/>
  <dep from="10" to="8" type="det"/>
  <dep from="10" to="9" type="compound"/>
  <dep from="7" to="10" type="dobj"/>
  <dep from="7" to="11" type="cc"/>
  <dep from="7" to="12" type="conj"/>
  <dep from="15" to="13" type="det"/>
  <dep from="15" to="14" type="amod"/>
  <dep from="12" to="15" type="dobj"/>
  <dep from="15" to="16" type="prep"/>
  <dep from="20" to="17" type="nmod"/>
  <dep from="17" to="18" type="cc"/>
  <dep from="17" to="19" type="conj"/>
  <dep from="16" to="20" type="pobj"/>
  <dep from="12" to="21" type="prep"/>
  <dep from="21" to="22" type="pobj"/>
  <dep from="12" to="23" type="prep"/>
  <dep from="25" to="24" type="det"/>
  <dep from="23" to="25" type="pobj"/>
  <dep from="3" to="26" type="punct"/>
 </dependencies>
 <semantics>
  <frameSemantics>
   <frame name="Perception_active">
    <lexicalUnit>
     <token id="15"/>
    </lexicalUnit>
    <frameElement type="Manner">
     <token id="14"/>
    </frameElement>
    <frameElement type="Perceiver_agentive">
     <token id="16"/>
     <token id="17"/>
     <token id="18"/>
     <token id="19"/>
    </frameElement>
   </frame>
  </frameSemantics>
 </semantics>
</command>