<?xml version="1.0" encoding="utf-8"?>
<command id="401331">
 <sentence>
  Yanto cast a cautious look towards the gamekeeper 's tower , but it appeared to be deserted ` Well , there 's one way to find out .
 </sentence>
 <tokens>
  <token id="1" lemma="yanto" pos="NNP" surface="Yanto"/>
  <token id="2" lemma="cast" pos="VBD" surface="cast"/>
  <token id="3" lemma="a" pos="DT" surface="a"/>
  <token id="4" lemma="cautious" pos="JJ" surface="cautious"/>
  <token id="5" lemma="look" pos="NN" surface="look"/>
  <token id="6" lemma="towards" pos="IN" surface="towards"/>
  <token id="7" lemma="the" pos="DT" surface="the"/>
  <token id="8" lemma="gamekeeper" pos="NN" surface="gamekeeper"/>
  <token id="9" lemma="'s" pos="POS" surface="'s"/>
  <token id="10" lemma="tower" pos="NN" surface="tower"/>
  <token id="11" lemma="," pos="," surface=","/>
  <token id="12" lemma="but" pos="CC" surface="but"/>
  <token id="13" lemma="-PRON-" pos="PRP" surface="it"/>
  <token id="14" lemma="appear" pos="VBD" surface="appeared"/>
  <token id="15" lemma="to" pos="TO" surface="to"/>
  <token id="16" lemma="be" pos="VB" surface="be"/>
  <token id="17" lemma="desert" pos="VBN" surface="deserted"/>
  <token id="18" lemma="`" pos="''" surface="`"/>
  <token id="19" lemma="well" pos="UH" surface="Well"/>
  <token id="20" lemma="," pos="," surface=","/>
  <token id="21" lemma="there" pos="EX" surface="there"/>
  <token id="22" lemma="be" pos="VBZ" surface="'s"/>
  <token id="23" lemma="one" pos="CD" surface="one"/>
  <token id="24" lemma="way" pos="NN" surface="way"/>
  <token id="25" lemma="to" pos="TO" surface="to"/>
  <token id="26" lemma="find" pos="VB" surface="find"/>
  <token id="27" lemma="out" pos="RP" surface="out"/>
  <token id="28" lemma="." pos="." surface="."/>
 </tokens>
 <dependencies>
  <dep from="2" to="1" type="nsubj"/>
  <dep from="0" to="2" type="root"/>
  <dep from="5" to="3" type="det"/>
  <dep from="5" to="4" type="amod"/>
  <dep from="2" to="5" type="dobj"/>
  <dep from="5" to="6" type="prep"/>
  <dep from="8" to="7" type="det"/>
  <dep from="10" to="8" type="poss"/>
  <dep from="8" to="9" type="case"/>
  <dep from="6" to="10" type="pobj"/>
  <dep from="2" to="11" type="punct"/>
  <dep from="2" to="12" type="cc"/>
  <dep from="14" to="13" type="nsubj"/>
  <dep from="2" to="14" type="conj"/>
  <dep from="17" to="15" type="aux"/>
  <dep from="17" to="16" type="auxpass"/>
  <dep from="14" to="17" type="xcomp"/>
  <dep from="22" to="18" type="punct"/>
  <dep from="22" to="19" type="intj"/>
  <dep from="22" to="20" type="punct"/>
  <dep from="22" to="21" type="expl"/>
  <dep from="14" to="22" type="parataxis"/>
  <dep from="24" to="23" type="nummod"/>
  <dep from="22" to="24" type="attr"/>
  <dep from="26" to="25" type="aux"/>
  <dep from="24" to="26" type="relcl"/>
  <dep from="26" to="27" type="prt"/>
  <dep from="14" to="28" type="punct"/>
 </dependencies>
 <semantics>
  <frameSemantics>
   <frame name="Perception_active">
    <lexicalUnit>
     <token id="5"/>
    </lexicalUnit>
    <frameElement type="Perceiver_agentive">
     <token id="1"/>
    </frameElement>
    <frameElement type="Manner">
     <token id="4"/>
    </frameElement>
    <frameElement type="Direction">
     <token id="6"/>
     <token id="7"/>
     <token id="8"/>
     <token id="9"/>
     <token id="10"/>
    </frameElement>
   </frame>
  </frameSemantics>
 </semantics>
</command>