<?xml version="1.0" encoding="utf-8"?>
<command id="707984">
 <sentence>
  When everyone is happy with the page , the metal is wheeled over to a large proofing press , which makes a positive impression of very high quality .
 </sentence>
 <tokens>
  <token id="1" lemma="when" pos="WRB" surface="When"/>
  <token id="2" lemma="everyone" pos="NN" surface="everyone"/>
  <token id="3" lemma="be" pos="VBZ" surface="is"/>
  <token id="4" lemma="happy" pos="JJ" surface="happy"/>
  <token id="5" lemma="with" pos="IN" surface="with"/>
  <token id="6" lemma="the" pos="DT" surface="the"/>
  <token id="7" lemma="page" pos="NN" surface="page"/>
  <token id="8" lemma="," pos="," surface=","/>
  <token id="9" lemma="the" pos="DT" surface="the"/>
  <token id="10" lemma="metal" pos="NN" surface="metal"/>
  <token id="11" lemma="be" pos="VBZ" surface="is"/>
  <token id="12" lemma="wheel" pos="VBN" surface="wheeled"/>
  <token id="13" lemma="over" pos="RP" surface="over"/>
  <token id="14" lemma="to" pos="IN" surface="to"/>
  <token id="15" lemma="a" pos="DT" surface="a"/>
  <token id="16" lemma="large" pos="JJ" surface="large"/>
  <token id="17" lemma="proofing" pos="NN" surface="proofing"/>
  <token id="18" lemma="press" pos="NN" surface="press"/>
  <token id="19" lemma="," pos="," surface=","/>
  <token id="20" lemma="which" pos="WDT" surface="which"/>
  <token id="21" lemma="make" pos="VBZ" surface="makes"/>
  <token id="22" lemma="a" pos="DT" surface="a"/>
  <token id="23" lemma="positive" pos="JJ" surface="positive"/>
  <token id="24" lemma="impression" pos="NN" surface="impression"/>
  <token id="25" lemma="of" pos="IN" surface="of"/>
  <token id="26" lemma="very" pos="RB" surface="very"/>
  <token id="27" lemma="high" pos="JJ" surface="high"/>
  <token id="28" lemma="quality" pos="NN" surface="quality"/>
  <token id="29" lemma="." pos="." surface="."/>
 </tokens>
 <dependencies>
  <dep from="3" to="1" type="advmod"/>
  <dep from="3" to="2" type="nsubj"/>
  <dep from="12" to="3" type="advcl"/>
  <dep from="3" to="4" type="acomp"/>
  <dep from="4" to="5" type="prep"/>
  <dep from="7" to="6" type="det"/>
  <dep from="5" to="7" type="pobj"/>
  <dep from="12" to="8" type="punct"/>
  <dep from="10" to="9" type="det"/>
  <dep from="12" to="10" type="nsubjpass"/>
  <dep from="12" to="11" type="auxpass"/>
  <dep from="0" to="12" type="root"/>
  <dep from="12" to="13" type="prt"/>
  <dep from="12" to="14" type="prep"/>
  <dep from="18" to="15" type="det"/>
  <dep from="18" to="16" type="amod"/>
  <dep from="18" to="17" type="compound"/>
  <dep from="14" to="18" type="pobj"/>
  <dep from="18" to="19" type="punct"/>
  <dep from="21" to="20" type="nsubj"/>
  <dep from="18" to="21" type="relcl"/>
  <dep from="24" to="22" type="det"/>
  <dep from="24" to="23" type="amod"/>
  <dep from="21" to="24" type="dobj"/>
  <dep from="24" to="25" type="prep"/>
  <dep from="27" to="26" type="advmod"/>
  <dep from="28" to="27" type="amod"/>
  <dep from="25" to="28" type="pobj"/>
  <dep from="12" to="29" type="punct"/>
 </dependencies>
 <semantics>
  <frameSemantics>
   <frame name="Bringing">
    <lexicalUnit>
     <token id="12"/>
    </lexicalUnit>
    <frameElement type="Theme">
     <token id="9"/>
     <token id="10"/>
    </frameElement>
    <frameElement type="Path">
     <token id="13"/>
    </frameElement>
    <frameElement type="Goal">
     <token id="14"/>
     <token id="15"/>
     <token id="16"/>
     <token id="17"/>
     <token id="18"/>
    </frameElement>
   </frame>
  </frameSemantics>
 </semantics>
</command>