<?xml version="1.0" encoding="utf-8"?>
<command id="783744">
 <sentence>
  Use a little royal icing to cement the two pieces of roof on to the sloping sides of the house , propping up the eaves with toothpicks too if necessary .
 </sentence>
 <tokens>
  <token id="1" lemma="use" pos="VB" surface="Use"/>
  <token id="2" lemma="a" pos="DT" surface="a"/>
  <token id="3" lemma="little" pos="JJ" surface="little"/>
  <token id="4" lemma="royal" pos="JJ" surface="royal"/>
  <token id="5" lemma="icing" pos="NN" surface="icing"/>
  <token id="6" lemma="to" pos="TO" surface="to"/>
  <token id="7" lemma="cement" pos="VB" surface="cement"/>
  <token id="8" lemma="the" pos="DT" surface="the"/>
  <token id="9" lemma="two" pos="CD" surface="two"/>
  <token id="10" lemma="piece" pos="NNS" surface="pieces"/>
  <token id="11" lemma="of" pos="IN" surface="of"/>
  <token id="12" lemma="roof" pos="NN" surface="roof"/>
  <token id="13" lemma="on" pos="IN" surface="on"/>
  <token id="14" lemma="to" pos="IN" surface="to"/>
  <token id="15" lemma="the" pos="DT" surface="the"/>
  <token id="16" lemma="slop" pos="VBG" surface="sloping"/>
  <token id="17" lemma="side" pos="NNS" surface="sides"/>
  <token id="18" lemma="of" pos="IN" surface="of"/>
  <token id="19" lemma="the" pos="DT" surface="the"/>
  <token id="20" lemma="house" pos="NN" surface="house"/>
  <token id="21" lemma="," pos="," surface=","/>
  <token id="22" lemma="prop" pos="VBG" surface="propping"/>
  <token id="23" lemma="up" pos="RP" surface="up"/>
  <token id="24" lemma="the" pos="DT" surface="the"/>
  <token id="25" lemma="eaf" pos="NNS" surface="eaves"/>
  <token id="26" lemma="with" pos="IN" surface="with"/>
  <token id="27" lemma="toothpick" pos="NNS" surface="toothpicks"/>
  <token id="28" lemma="too" pos="RB" surface="too"/>
  <token id="29" lemma="if" pos="IN" surface="if"/>
  <token id="30" lemma="necessary" pos="JJ" surface="necessary"/>
  <token id="31" lemma="." pos="." surface="."/>
 </tokens>
 <dependencies>
  <dep from="0" to="1" type="root"/>
  <dep from="5" to="2" type="det"/>
  <dep from="5" to="3" type="amod"/>
  <dep from="5" to="4" type="amod"/>
  <dep from="1" to="5" type="dobj"/>
  <dep from="7" to="6" type="aux"/>
  <dep from="1" to="7" type="xcomp"/>
  <dep from="10" to="8" type="det"/>
  <dep from="10" to="9" type="nummod"/>
  <dep from="7" to="10" type="dobj"/>
  <dep from="10" to="11" type="prep"/>
  <dep from="11" to="12" type="pobj"/>
  <dep from="7" to="13" type="prep"/>
  <dep from="7" to="14" type="prep"/>
  <dep from="17" to="15" type="det"/>
  <dep from="17" to="16" type="amod"/>
  <dep from="14" to="17" type="pobj"/>
  <dep from="17" to="18" type="prep"/>
  <dep from="20" to="19" type="det"/>
  <dep from="18" to="20" type="pobj"/>
  <dep from="7" to="21" type="punct"/>
  <dep from="1" to="22" type="advcl"/>
  <dep from="22" to="23" type="prt"/>
  <dep from="25" to="24" type="det"/>
  <dep from="22" to="25" type="dobj"/>
  <dep from="25" to="26" type="prep"/>
  <dep from="26" to="27" type="pobj"/>
  <dep from="30" to="28" type="advmod"/>
  <dep from="30" to="29" type="mark"/>
  <dep from="22" to="30" type="advcl"/>
  <dep from="1" to="31" type="punct"/>
 </dependencies>
 <semantics>
  <frameSemantics>
   <frame name="Attaching">
    <lexicalUnit>
     <token id="7"/>
    </lexicalUnit>
    <frameElement type="Item">
     <token id="8"/>
     <token id="9"/>
     <token id="10"/>
     <token id="11"/>
     <token id="12"/>
    </frameElement>
    <frameElement type="Goal">
     <token id="13"/>
     <token id="14"/>
     <token id="15"/>
     <token id="16"/>
     <token id="17"/>
     <token id="18"/>
     <token id="19"/>
     <token id="20"/>
    </frameElement>
    <frameElement type="Connector">
     <token id="7"/>
    </frameElement>
   </frame>
  </frameSemantics>
 </semantics>
</command>