<?xml version="1.0" encoding="utf-8"?>
<command id="2824435">
	<sentence>I felt the temblor begin and glanced at the table next to mine , smiled that guilty smile and we both mouthed the words , `` Earth-quake ! '' together .</sentence>
	<tokens>
		<token id="1" lemma="I" pos="PP" surface="I"/>
		<token id="2" lemma="felt" pos="VVD" surface="felt"/>
		<token id="3" lemma="the" pos="dt" surface="the"/>
		<token id="4" lemma="temblor" pos="nn" surface="temblor"/>
		<token id="5" lemma="begin" pos="VV" surface="begin"/>
		<token id="6" lemma="and" pos="cc" surface="and"/>
		<token id="7" lemma="glanced" pos="VVD" surface="glanced"/>
		<token id="8" lemma="at" pos="in" surface="at"/>
		<token id="9" lemma="the" pos="dt" surface="the"/>
		<token id="10" lemma="table" pos="nn" surface="table"/>
		<token id="11" lemma="next" pos="jj" surface="next"/>
		<token id="12" lemma="to" pos="to" surface="to"/>
		<token id="13" lemma="mine" pos="nn" surface="mine"/>
		<token id="14" lemma="," pos="," surface=","/>
		<token id="15" lemma="smiled" pos="VVD" surface="smiled"/>
		<token id="16" lemma="that" pos="dt" surface="that"/>
		<token id="17" lemma="guilty" pos="jj" surface="guilty"/>
		<token id="18" lemma="smile" pos="nn" surface="smile"/>
		<token id="19" lemma="and" pos="cc" surface="and"/>
		<token id="20" lemma="we" pos="PP" surface="we"/>
		<token id="21" lemma="both" pos="dt" surface="both"/>
		<token id="22" lemma="mouthed" pos="VVD" surface="mouthed"/>
		<token id="23" lemma="the" pos="dt" surface="the"/>
		<token id="24" lemma="words" pos="nns" surface="words"/>
		<token id="25" lemma="," pos="," surface=","/>
		<token id="26" lemma="``" pos="``" surface="``"/>
		<token id="27" lemma="Earth-quake" pos="nn" surface="Earth-quake"/>
		<token id="28" lemma="!" pos="sent" surface="!"/>
		<token id="29" lemma="''" pos="''" surface="''"/>
		<token id="30" lemma="together" pos="rb" surface="together"/>
		<token id="31" lemma="." pos="sent" surface="."/>
	</tokens>
	<semantics>
		<frameSemantics>
			<frame name="Perception_active">
				<lexicalUnit>
					<token id="7"/>
				</lexicalUnit>
				<frameElement type="Perceiver_agentive">
					<token id="1"/>
				</frameElement>
				<frameElement type="Phenomenon">
					<token id="8"/>
					<token id="9"/>
					<token id="10"/>
					<token id="11"/>
					<token id="12"/>
					<token id="13"/>
				</frameElement>
			</frame>
		</frameSemantics>
	</semantics>
</command>
