<?xml version="1.0" encoding="utf-8"?>
<command id="4099703">
	<sentence>Two main factories located in the cities of Kanggye and Sakchu are reportedly tasked with the final preparation , filling , and distribution of CW agents in artillery shells from 80 mm and larger , as well as 240 mm caliber artillery rockets .</sentence>
	<tokens>
		<token id="1" lemma="Two" pos="cd" surface="Two"/>
		<token id="2" lemma="main" pos="jj" surface="main"/>
		<token id="3" lemma="factories" pos="nns" surface="factories"/>
		<token id="4" lemma="located" pos="VVN" surface="located"/>
		<token id="5" lemma="in" pos="in" surface="in"/>
		<token id="6" lemma="the" pos="dt" surface="the"/>
		<token id="7" lemma="cities" pos="nns" surface="cities"/>
		<token id="8" lemma="of" pos="in" surface="of"/>
		<token id="9" lemma="Kanggye" pos="NP" surface="Kanggye"/>
		<token id="10" lemma="and" pos="cc" surface="and"/>
		<token id="11" lemma="Sakchu" pos="NP" surface="Sakchu"/>
		<token id="12" lemma="are" pos="vbp" surface="are"/>
		<token id="13" lemma="reportedly" pos="rb" surface="reportedly"/>
		<token id="14" lemma="tasked" pos="VVN" surface="tasked"/>
		<token id="15" lemma="with" pos="in" surface="with"/>
		<token id="16" lemma="the" pos="dt" surface="the"/>
		<token id="17" lemma="final" pos="jj" surface="final"/>
		<token id="18" lemma="preparation" pos="nn" surface="preparation"/>
		<token id="19" lemma="," pos="," surface=","/>
		<token id="20" lemma="filling" pos="VVG" surface="filling"/>
		<token id="21" lemma="," pos="," surface=","/>
		<token id="22" lemma="and" pos="cc" surface="and"/>
		<token id="23" lemma="distribution" pos="nn" surface="distribution"/>
		<token id="24" lemma="of" pos="in" surface="of"/>
		<token id="25" lemma="CW" pos="jj" surface="CW"/>
		<token id="26" lemma="agents" pos="nns" surface="agents"/>
		<token id="27" lemma="in" pos="in" surface="in"/>
		<token id="28" lemma="artillery" pos="nn" surface="artillery"/>
		<token id="29" lemma="shells" pos="nns" surface="shells"/>
		<token id="30" lemma="from" pos="in" surface="from"/>
		<token id="31" lemma="80" pos="cd" surface="80"/>
		<token id="32" lemma="mm" pos="nn" surface="mm"/>
		<token id="33" lemma="and" pos="cc" surface="and"/>
		<token id="34" lemma="larger" pos="jjr" surface="larger"/>
		<token id="35" lemma="," pos="," surface=","/>
		<token id="36" lemma="as" pos="rb" surface="as"/>
		<token id="37" lemma="well" pos="rb" surface="well"/>
		<token id="38" lemma="as" pos="in" surface="as"/>
		<token id="39" lemma="240" pos="cd" surface="240"/>
		<token id="40" lemma="mm" pos="nn" surface="mm"/>
		<token id="41" lemma="caliber" pos="nn" surface="caliber"/>
		<token id="42" lemma="artillery" pos="nn" surface="artillery"/>
		<token id="43" lemma="rockets" pos="nns" surface="rockets"/>
		<token id="44" lemma="." pos="sent" surface="."/>
	</tokens>
	<semantics>
		<frameSemantics>
			<frame name="Being_located">
				<lexicalUnit>
					<token id="4"/>
				</lexicalUnit>
				<frameElement type="Theme">
					<token id="1"/>
					<token id="2"/>
					<token id="3"/>
				</frameElement>
				<frameElement type="Location">
					<token id="5"/>
					<token id="6"/>
					<token id="7"/>
					<token id="8"/>
					<token id="9"/>
					<token id="10"/>
					<token id="11"/>
				</frameElement>
			</frame>
		</frameSemantics>
	</semantics>
</command>
