<?xml version="1.0" encoding="utf-8"?>
<command id="4102452">
	<sentence>Paula_Zahn : I know you 've had a chance to study the the plan the president put forth today .</sentence>
	<tokens>
		<token id="1" lemma="Paula_Zahn" pos="NP" surface="Paula_Zahn"/>
		<token id="2" lemma=":" pos=":" surface=":"/>
		<token id="3" lemma="I" pos="PP" surface="I"/>
		<token id="4" lemma="know" pos="VVP" surface="know"/>
		<token id="5" lemma="you" pos="PP" surface="you"/>
		<token id="6" lemma="'ve" pos="VHP" surface="'ve"/>
		<token id="7" lemma="had" pos="VHD" surface="had"/>
		<token id="8" lemma="a" pos="dt" surface="a"/>
		<token id="9" lemma="chance" pos="nn" surface="chance"/>
		<token id="10" lemma="to" pos="to" surface="to"/>
		<token id="11" lemma="study" pos="VV" surface="study"/>
		<token id="12" lemma="the" pos="dt" surface="the"/>
		<token id="13" lemma="the" pos="dt" surface="the"/>
		<token id="14" lemma="plan" pos="nn" surface="plan"/>
		<token id="15" lemma="the" pos="dt" surface="the"/>
		<token id="16" lemma="president" pos="nn" surface="president"/>
		<token id="17" lemma="put" pos="VVD" surface="put"/>
		<token id="18" lemma="forth" pos="rb" surface="forth"/>
		<token id="19" lemma="today" pos="nn" surface="today"/>
		<token id="20" lemma="." pos="sent" surface="."/>
	</tokens>
	<semantics>
		<frameSemantics>
			<frame name="Searching">
				<lexicalUnit>
					<token id="11"/>
				</lexicalUnit>
				<frameElement type="Ground">
					<token id="12"/>
					<token id="13"/>
					<token id="14"/>
					<token id="15"/>
					<token id="16"/>
					<token id="17"/>
					<token id="18"/>
					<token id="19"/>
				</frameElement>
				<frameElement type="Cognizer">
					<token id="5"/>
				</frameElement>
			</frame>
		</frameSemantics>
	</semantics>
</command>
